{
  "items": {
    "215731": {
      "content_sha1": "769741cd894d5eecc0c863e8c2b5886c763c6852",
      "data_file": "articles.jsonl",
      "fallback": "none",
      "fetch_status": "ok",
      "published_at": "2026-06-12T08:00:25",
      "saved_at": "2026-06-13T00:02:24+00:00",
      "source": "gcores.com",
      "source_key": "gcores",
      "title": "Steam周销量排行榜:《极限竞速：地平线6》登顶|2026年6月第1周",
      "url": "https://www.gcores.com/articles/215731"
    },
    "215733": {
      "content_sha1": "9f686966798205ad7810bf28b5bb632ee094b16e",
      "data_file": "articles.jsonl",
      "fallback": "none",
      "fetch_status": "ok",
      "published_at": "2026-06-12T08:00:25",
      "saved_at": "2026-06-13T00:02:14+00:00",
      "source": "gcores.com",
      "source_key": "gcores",
      "title": "《彩虹六号：围攻》X《黎明杀机》联动活动现已实装",
      "url": "https://www.gcores.com/articles/215733"
    },
    "215734": {
      "content_sha1": "2ddc071b18e41ce5406fc2d1c3cea667d2215bf3",
      "data_file": "articles.jsonl",
      "fallback": "none",
      "fetch_status": "ok",
      "published_at": "2026-06-12T08:00:25",
      "saved_at": "2026-06-13T00:02:29+00:00",
      "source": "gcores.com",
      "source_key": "gcores",
      "title": "任天堂因Joy-Con漂移问题被罚超3500万欧元",
      "url": "https://www.gcores.com/articles/215734"
    },
    "215735": {
      "content_sha1": "8f340929d0de263c77af2501d04a94c890216f10",
      "data_file": "articles.jsonl",
      "fallback": "none",
      "fetch_status": "ok",
      "published_at": "2026-06-12T08:00:25",
      "saved_at": "2026-06-13T00:02:09+00:00",
      "source": "gcores.com",
      "source_key": "gcores",
      "title": "《展翅翱翔》确认推出鸟类牌包季票，路线图同步揭晓",
      "url": "https://www.gcores.com/articles/215735"
    },
    "215739": {
      "content_sha1": "c229191a4e7c9e6937624031428a226814c4b421",
      "data_file": "articles.jsonl",
      "fallback": "none",
      "fetch_status": "ok",
      "published_at": "2026-06-12T08:00:25",
      "saved_at": "2026-06-13T00:02:19+00:00",
      "source": "gcores.com",
      "source_key": "gcores",
      "title": "《神鬼寓言》30分钟实机演示",
      "url": "https://www.gcores.com/articles/215739"
    },
    "215741": {
      "content_sha1": "b9b9013a91fac888979c0ddbd552b2085b73cc8f",
      "data_file": "articles.jsonl",
      "fallback": "none",
      "fetch_status": "ok",
      "published_at": "2026-06-12T08:00:25",
      "saved_at": "2026-06-13T00:02:04+00:00",
      "source": "gcores.com",
      "source_key": "gcores",
      "title": "育碧宣布关闭温尼伯和贝尔格莱德工作室，至多380人将受影响",
      "url": "https://www.gcores.com/articles/215741"
    },
    "215743": {
      "content_sha1": "604b0f4823dd8fffce57debbfc3b9112685345f1",
      "data_file": "articles.jsonl",
      "fallback": "none",
      "fetch_status": "ok",
      "published_at": "2026-06-12T08:00:25",
      "saved_at": "2026-06-13T00:01:59+00:00",
      "source": "gcores.com",
      "source_key": "gcores",
      "title": "Xbox 拟进一步裁员，官方称将对公司进行“重置”",
      "url": "https://www.gcores.com/articles/215743"
    },
    "215744": {
      "content_sha1": "1a28649495e8bb219e02d09cafe8563bd5349892",
      "data_file": "articles.jsonl",
      "fallback": "none",
      "fetch_status": "ok",
      "published_at": "2026-06-12T08:00:25",
      "saved_at": "2026-06-13T00:01:54+00:00",
      "source": "gcores.com",
      "source_key": "gcores",
      "title": "《1666：阿姆斯特丹》序章试玩被指含AI资产，开发商道歉并承诺正式版不使用AI",
      "url": "https://www.gcores.com/articles/215744"
    },
    "215748": {
      "content_sha1": "1c7bc0ae643a6aae4b1170a859fc017fbcece906",
      "data_file": "articles.jsonl",
      "fallback": "none",
      "fetch_status": "ok",
      "published_at": "2026-06-12T08:00:25",
      "saved_at": "2026-06-13T00:01:48+00:00",
      "source": "gcores.com",
      "source_key": "gcores",
      "title": "《生化危机RE: 维罗妮卡》愿望单突破 100万，将于2027年发售",
      "url": "https://www.gcores.com/articles/215748"
    },
    "215751": {
      "content_sha1": "3a8cb155cd825637eeb996f1ce0eb92ca0736cd5",
      "data_file": "articles.jsonl",
      "fallback": "none",
      "fetch_status": "ok",
      "published_at": "2026-06-12T08:00:25",
      "saved_at": "2026-06-13T00:01:43+00:00",
      "source": "gcores.com",
      "source_key": "gcores",
      "title": "《红色沙漠》全球累计销量现已突破600万份",
      "url": "https://www.gcores.com/articles/215751"
    },
    "215752": {
      "content_sha1": "a87451c09a5b92e7b31f22cb404105c581b24c5e",
      "data_file": "articles.jsonl",
      "fallback": "none",
      "fetch_status": "ok",
      "published_at": "2026-06-12T08:00:25",
      "saved_at": "2026-06-13T00:01:39+00:00",
      "source": "gcores.com",
      "source_key": "gcores",
      "title": "《使命召唤：现代战争4》公开无人区搜打撤模式革新玩法",
      "url": "https://www.gcores.com/articles/215752"
    },
    "215760": {
      "content_sha1": "4e5b51e6b91b3b06a4e6f634c3b60daff95e1a66",
      "data_file": "articles.jsonl",
      "fallback": "none",
      "fetch_status": "ok",
      "published_at": "2026-06-12T08:00:23",
      "saved_at": "2026-06-13T00:01:34+00:00",
      "source": "gcores.com",
      "source_key": "gcores",
      "title": "RTS肉鸽自走棋《铁甲狂潮》全新试玩版现已上线！无需微操，指挥钢铁大军浴血废土",
      "url": "https://www.gcores.com/articles/215760"
    },
    "215761": {
      "content_sha1": "d213c9f3db42792a867e7bbaab61bc8a80cf65a4",
      "data_file": "articles.jsonl",
      "fallback": "none",
      "fetch_status": "ok",
      "published_at": "2026-06-12T08:00:23",
      "saved_at": "2026-06-13T00:01:29+00:00",
      "source": "gcores.com",
      "source_key": "gcores",
      "title": "【抽奖】国产多人动作肉鸽《失落城堡2》1.0正式上线，属于宝藏猎人的最终冒险开启",
      "url": "https://www.gcores.com/articles/215761"
    },
    "215768": {
      "content_sha1": "17d33cc02da9bc19438682e43da7cf56f52901d5",
      "data_file": "articles.jsonl",
      "fallback": "none",
      "fetch_status": "ok",
      "published_at": "2026-06-12T08:00:23",
      "saved_at": "2026-06-13T00:01:24+00:00",
      "source": "gcores.com",
      "source_key": "gcores",
      "title": "《巫术》系列45周年纪念主视觉图公开，由末弥纯绘制",
      "url": "https://www.gcores.com/articles/215768"
    },
    "215769": {
      "content_sha1": "16d9f64b5ea11c85b2f5a96b719ecbb5fadfbbc9",
      "data_file": "articles.jsonl",
      "fallback": "none",
      "fetch_status": "ok",
      "published_at": "2026-06-12T08:00:23",
      "saved_at": "2026-06-13T00:01:19+00:00",
      "source": "gcores.com",
      "source_key": "gcores",
      "title": "《轮回之兽》配音阵容公布！2B、苇名一心等角色声优倾情献声！",
      "url": "https://www.gcores.com/articles/215769"
    },
    "215772": {
      "content_sha1": "178ecaf95bc1ccf03b2114907a14d489aaa05fd9",
      "data_file": "articles.jsonl",
      "fallback": "none",
      "fetch_status": "ok",
      "published_at": "2026-06-12T08:00:23",
      "saved_at": "2026-06-13T00:01:14+00:00",
      "source": "gcores.com",
      "source_key": "gcores",
      "title": "《开球! REMATCH》第 4 赛季：Rematch国家杯火热开赛，到你上场了！",
      "url": "https://www.gcores.com/articles/215772"
    },
    "215774": {
      "content_sha1": "0ed540d6b4083fafa9e925bde03b59e624ca98e6",
      "data_file": "articles.jsonl",
      "fallback": "none",
      "fetch_status": "ok",
      "published_at": "2026-06-12T08:00:23",
      "saved_at": "2026-06-13T00:01:09+00:00",
      "source": "gcores.com",
      "source_key": "gcores",
      "title": "全速前进！《一起开火车 2：汽笛重鸣》今日正式发售",
      "url": "https://www.gcores.com/articles/215774"
    },
    "215775": {
      "content_sha1": "88651895a69999b6ca4bbf0e89b3065276a8a3bd",
      "data_file": "articles.jsonl",
      "fallback": "none",
      "fetch_status": "ok",
      "published_at": "2026-06-12T08:00:23",
      "saved_at": "2026-06-13T00:00:57+00:00",
      "source": "gcores.com",
      "source_key": "gcores",
      "title": "【抽奖】人狼村之谜姊妹作《DMLC！》将推出主机平台中文版",
      "url": "https://www.gcores.com/articles/215775"
    },
    "215776": {
      "content_sha1": "05881ebca4a8b5b726d25d9c403dc4fca93d3d4d",
      "data_file": "articles.jsonl",
      "fallback": "none",
      "fetch_status": "ok",
      "published_at": "2026-06-12T08:00:23",
      "saved_at": "2026-06-13T00:01:05+00:00",
      "source": "gcores.com",
      "source_key": "gcores",
      "title": "《罪恶装备 奋战》5周年暨系列28周年纪念节目6月23日播出",
      "url": "https://www.gcores.com/articles/215776"
    },
    "215778": {
      "content_sha1": "29d2260479c890d4fea4d9edfb6671badd987f76",
      "data_file": "articles.jsonl",
      "fallback": "none",
      "fetch_status": "ok",
      "published_at": "2026-06-12T08:00:23",
      "saved_at": "2026-06-13T00:00:51+00:00",
      "source": "gcores.com",
      "source_key": "gcores",
      "title": "【抽奖】《人形之伤迹》NS中文版将于6月11日登陆港台eShop",
      "url": "https://www.gcores.com/articles/215778"
    },
    "215780": {
      "content_sha1": "87218887deca481305dbfadfe2e1f457e9ae56b0",
      "data_file": "articles.jsonl",
      "fallback": "none",
      "fetch_status": "ok",
      "published_at": "2026-06-12T08:00:23",
      "saved_at": "2026-06-13T00:00:42+00:00",
      "source": "gcores.com",
      "source_key": "gcores",
      "title": "结束25年的历程：Nexon旗下《泡泡堂》将于8月13日上午9点停止服务",
      "url": "https://www.gcores.com/articles/215780"
    },
    "215786": {
      "content_sha1": "562460182d58e12dfff12c0426c2e46ff0d57435",
      "data_file": "articles.jsonl",
      "fallback": "none",
      "fetch_status": "ok",
      "published_at": "2026-06-12T08:00:23",
      "saved_at": "2026-06-13T00:00:36+00:00",
      "source": "gcores.com",
      "source_key": "gcores",
      "title": "中国游戏史征集｜哪款游戏，曾经代表了你的一年？",
      "url": "https://www.gcores.com/articles/215786"
    },
    "215793": {
      "content_sha1": "8e69808d5f72d5f3318d51ad9a06d5ddbce91be4",
      "data_file": "articles.jsonl",
      "fallback": "none",
      "fetch_status": "ok",
      "published_at": "2026-06-12T10:00:23",
      "saved_at": "2026-06-13T00:02:50+00:00",
      "source": "gcores.com",
      "source_key": "gcores",
      "title": "Epic喜加二：《战锤40K：极速狂飙》及《衔尾蛇国王》免费领",
      "url": "https://www.gcores.com/articles/215793"
    },
    "215794": {
      "content_sha1": "2e0afa820b508c868d2a487619c1cc4e5eb3d57e",
      "data_file": "articles.jsonl",
      "fallback": "none",
      "fetch_status": "ok",
      "published_at": "2026-06-12T10:00:23",
      "saved_at": "2026-06-13T00:02:45+00:00",
      "source": "gcores.com",
      "source_key": "gcores",
      "title": "《摸鱼园丁》正式公布，将于2027年发售",
      "url": "https://www.gcores.com/articles/215794"
    },
    "215795": {
      "content_sha1": "4254ec3f94eef2ae019ea535d904274afc969634",
      "data_file": "articles.jsonl",
      "fallback": "none",
      "fetch_status": "ok",
      "published_at": "2026-06-12T10:00:23",
      "saved_at": "2026-06-13T00:02:55+00:00",
      "source": "gcores.com",
      "source_key": "gcores",
      "title": "类魂动作游戏《不朽遗志》延期至10月13日发售",
      "url": "https://www.gcores.com/articles/215795"
    },
    "215797": {
      "content_sha1": "580c80dec976c1b5c56d3c9320c1973514b39ba2",
      "data_file": "articles.jsonl",
      "fallback": "none",
      "fetch_status": "ok",
      "published_at": "2026-06-12T10:00:23",
      "saved_at": "2026-06-13T00:02:40+00:00",
      "source": "gcores.com",
      "source_key": "gcores",
      "title": "Steam喜加一：叙事冒险游戏《红灯笼》免费领",
      "url": "https://www.gcores.com/articles/215797"
    },
    "215800": {
      "content_sha1": "8fb6d5edecbc23a983ea2a08e11f2318055e5ad2",
      "data_file": "articles.jsonl",
      "fallback": "none",
      "fetch_status": "ok",
      "published_at": "2026-06-12T10:00:23",
      "saved_at": "2026-06-13T00:02:35+00:00",
      "source": "gcores.com",
      "source_key": "gcores",
      "title": "2026年Summer Game Fest创下收视新高，直播观看次数达6200万",
      "url": "https://www.gcores.com/articles/215800"
    },
    "215801": {
      "content_sha1": "a70fc3b6ed9c3112b55985f7710a14eea8332bf9",
      "data_file": "articles.jsonl",
      "fallback": "none",
      "fetch_status": "ok",
      "published_at": "2026-06-12T11:00:23",
      "saved_at": "2026-06-13T00:03:11+00:00",
      "source": "gcores.com",
      "source_key": "gcores",
      "title": "《极限竞速：地平线 6》部分玩家存档丢失，官方正在调查并公布应对措施",
      "url": "https://www.gcores.com/articles/215801"
    },
    "215803": {
      "content_sha1": "07895a6cff886c122e33229dbb12aa33be9bc482",
      "data_file": "articles.jsonl",
      "fallback": "none",
      "fetch_status": "ok",
      "published_at": "2026-06-12T11:00:23",
      "saved_at": "2026-06-13T00:03:07+00:00",
      "source": "gcores.com",
      "source_key": "gcores",
      "title": "《彼方的她2》确定登陆Steam新品节，新预告片公开",
      "url": "https://www.gcores.com/articles/215803"
    },
    "215804": {
      "content_sha1": "74574b99a5573e5c07f7aa8e4098c00e6c394600",
      "data_file": "articles.jsonl",
      "fallback": "none",
      "fetch_status": "ok",
      "published_at": "2026-06-12T11:00:14",
      "saved_at": "2026-06-13T00:03:00+00:00",
      "source": "gcores.com",
      "source_key": "gcores",
      "title": "与死神对赌！骰子肉鸽新作《赌命无常：出千为王》公开试玩版现已上线",
      "url": "https://www.gcores.com/articles/215804"
    },
    "215805": {
      "content_sha1": "776d8602e7b0a230bf8d2212f86b21930697a52f",
      "data_file": "articles.jsonl",
      "fallback": "none",
      "fetch_status": "ok",
      "published_at": "2026-06-12T12:00:14",
      "saved_at": "2026-06-13T00:03:26+00:00",
      "source": "gcores.com",
      "source_key": "gcores",
      "title": "太空死灵，植入物以及新同伴——《战锤40K：行商浪人》DLC3现已发售",
      "url": "https://www.gcores.com/articles/215805"
    },
    "215806": {
      "content_sha1": "77039838689cb47cee93708484fe333e07c2f720",
      "data_file": "articles.jsonl",
      "fallback": "none",
      "fetch_status": "ok",
      "published_at": "2026-06-12T12:00:14",
      "saved_at": "2026-06-13T00:03:21+00:00",
      "source": "gcores.com",
      "source_key": "gcores",
      "title": "《烤串大厨! 餐厅模拟器》1.0正式版现已在Steam发布，已获7,000余篇玩家评价",
      "url": "https://www.gcores.com/articles/215806"
    },
    "215808": {
      "content_sha1": "e814b381826bc66c918b8623843a0e37604aedd3",
      "data_file": "articles.jsonl",
      "fallback": "none",
      "fetch_status": "ok",
      "published_at": "2026-06-12T12:00:14",
      "saved_at": "2026-06-13T00:03:16+00:00",
      "source": "gcores.com",
      "source_key": "gcores",
      "title": "《狸狸：胖哒的夏日》Steam新品节demo现已上线，CRITICAL REFLEX公布多款新作动态",
      "url": "https://www.gcores.com/articles/215808"
    },
    "215820": {
      "content_sha1": "fa9a8345b0a8d25e1fe435bf8c38454beff20363",
      "data_file": "articles.jsonl",
      "fallback": "none",
      "fetch_status": "ok",
      "published_at": "2026-06-12T15:00:14",
      "saved_at": "2026-06-13T00:04:02+00:00",
      "source": "gcores.com",
      "source_key": "gcores",
      "title": "“日本游戏大赏2026”年度作品部门公众投票现已开始",
      "url": "https://www.gcores.com/articles/215820"
    },
    "215821": {
      "content_sha1": "fd3955c059aa6b3cc1d0832201483606d734d695",
      "data_file": "articles.jsonl",
      "fallback": "none",
      "fetch_status": "ok",
      "published_at": "2026-06-12T15:00:14",
      "saved_at": "2026-06-13T00:03:51+00:00",
      "source": "gcores.com",
      "source_key": "gcores",
      "title": "开放世界四人联机体素风新作《灵伴世界》免费试玩版现已上线",
      "url": "https://www.gcores.com/articles/215821"
    },
    "215822": {
      "content_sha1": "bf44e62d84dfa5f5530f77a367a1ac98a2ee9d57",
      "data_file": "articles.jsonl",
      "fallback": "none",
      "fetch_status": "ok",
      "published_at": "2026-06-12T15:00:14",
      "saved_at": "2026-06-13T00:03:56+00:00",
      "source": "gcores.com",
      "source_key": "gcores",
      "title": "《弧光猎人》国服首测“弧光测试”6月24日开启，预约已上线",
      "url": "https://www.gcores.com/articles/215822"
    },
    "215824": {
      "content_sha1": "c0fe71f9dbdedb4124437bd7a0db93834cace6cc",
      "data_file": "articles.jsonl",
      "fallback": "none",
      "fetch_status": "ok",
      "published_at": "2026-06-12T15:00:14",
      "saved_at": "2026-06-13T00:03:46+00:00",
      "source": "gcores.com",
      "source_key": "gcores",
      "title": "第一人称类魂《不朽遗志》发售延期至10月13日，Steam国区售价168元",
      "url": "https://www.gcores.com/articles/215824"
    },
    "215825": {
      "content_sha1": "8086459474b7830de6c01474bcda1d6c1a2aca34",
      "data_file": "articles.jsonl",
      "fallback": "none",
      "fetch_status": "ok",
      "published_at": "2026-06-12T15:00:14",
      "saved_at": "2026-06-13T00:03:40+00:00",
      "source": "gcores.com",
      "source_key": "gcores",
      "title": "《红色沙漠》举办“超越阿比斯：社区挑战活动”全球视频征集大赛",
      "url": "https://www.gcores.com/articles/215825"
    },
    "215826": {
      "content_sha1": "6c5bda00a555d239c5d46781acb597370e98f4c2",
      "data_file": "articles.jsonl",
      "fallback": "none",
      "fetch_status": "ok",
      "published_at": "2026-06-12T15:00:14",
      "saved_at": "2026-06-13T00:03:35+00:00",
      "source": "gcores.com",
      "source_key": "gcores",
      "title": "《Fate/Grand Order》6月中旬更新Unity 6引擎，约需额外16GB存储空间",
      "url": "https://www.gcores.com/articles/215826"
    },
    "215828": {
      "content_sha1": "51f842945e5e52a364ceaa22600e21a8247ca9c8",
      "data_file": "articles.jsonl",
      "fallback": "none",
      "fetch_status": "ok",
      "published_at": "2026-06-12T16:00:14",
      "saved_at": "2026-06-13T00:04:27+00:00",
      "source": "gcores.com",
      "source_key": "gcores",
      "title": "《蚀教追猎》将于本周五在摩点平台开始众筹",
      "url": "https://www.gcores.com/articles/215828"
    },
    "215830": {
      "content_sha1": "07ee8fba4f39c3761a882fac3259c90ec6a5c2f6",
      "data_file": "articles.jsonl",
      "fallback": "none",
      "fetch_status": "ok",
      "published_at": "2026-06-12T16:00:14",
      "saved_at": "2026-06-13T00:04:22+00:00",
      "source": "gcores.com",
      "source_key": "gcores",
      "title": "你说你这块石头里有什么？克系赌石模拟游戏《地渊珠宝匠》6月12日开启Steam免费测试！",
      "url": "https://www.gcores.com/articles/215830"
    },
    "215833": {
      "content_sha1": "9e8efe0bde438c5eeb8473f0da74c7b9f248daaf",
      "data_file": "articles.jsonl",
      "fallback": "none",
      "fetch_status": "ok",
      "published_at": "2026-06-12T16:00:14",
      "saved_at": "2026-06-13T00:04:17+00:00",
      "source": "gcores.com",
      "source_key": "gcores",
      "title": "据称 2K 曾有意开发 FIFA 授权足球游戏，谈判接近完成但最终告吹",
      "url": "https://www.gcores.com/articles/215833"
    },
    "215835": {
      "content_sha1": "a8aa3b279c672d2222c527eb5f824110f915d2f4",
      "data_file": "articles.jsonl",
      "fallback": "none",
      "fetch_status": "ok",
      "published_at": "2026-06-12T16:00:14",
      "saved_at": "2026-06-13T00:04:12+00:00",
      "source": "gcores.com",
      "source_key": "gcores",
      "title": "《命运石之门》动画放送15周年纪念展览会确定举办",
      "url": "https://www.gcores.com/articles/215835"
    },
    "215836": {
      "content_sha1": "35b63caeb35f1431417a86f613d1c01f6bad5503",
      "data_file": "articles.jsonl",
      "fallback": "none",
      "fetch_status": "ok",
      "published_at": "2026-06-12T16:00:14",
      "saved_at": "2026-06-13T00:04:07+00:00",
      "source": "gcores.com",
      "source_key": "gcores",
      "title": "布拉德·皮特携战犬荒野求生：电影《野兽之心》发布首支预告",
      "url": "https://www.gcores.com/articles/215836"
    },
    "215845": {
      "content_sha1": "84b75da30a776d47b6796c8b5b6e756b403cd75b",
      "data_file": "articles.jsonl",
      "fallback": "none",
      "fetch_status": "ok",
      "published_at": "2026-06-12T18:00:14",
      "saved_at": "2026-06-13T00:04:33+00:00",
      "source": "gcores.com",
      "source_key": "gcores",
      "title": "【抽奖】方寸之间，千军万马！Roguelike即时战略游戏《桌上谈兵》今日登陆Steam",
      "url": "https://www.gcores.com/articles/215845"
    },
    "215856": {
      "content_sha1": "80644c8d2e5c7fd9ec38d1d064591451be94ac61",
      "data_file": "articles.jsonl",
      "fallback": "none",
      "fetch_status": "ok",
      "published_at": "2026-06-12T21:00:14",
      "saved_at": "2026-06-13T00:04:38+00:00",
      "source": "gcores.com",
      "source_key": "gcores",
      "title": "《卡莉亚的炼金工房 ～夜之王国与追忆之道标～》公布最新情报",
      "url": "https://www.gcores.com/articles/215856"
    }
  }
}