{
  "items": {
    "liftoffs_437m_ipo_is_on_valuing_the_adtech_firm_4ab98986": {
      "content_sha1": "960da75baaedace297a26dc30ac71f20cf3b5922",
      "data_file": "articles.jsonl",
      "fallback": "none",
      "fetch_status": "ok",
      "published_at": "2026-06-04T17:17:51",
      "saved_at": "2026-06-05T00:08:17+00:00",
      "source": "mobilegamer.biz",
      "source_key": "mobilegamer",
      "title": "Liftoff’s IPO is back on – and values the adtech firm at $3.83bn",
      "url": "https://mobilegamer.biz/liftoffs-437m-ipo-is-on-valuing-the-adtech-firm-at-3-83bn/"
    },
    "pokemon_champions_is_coming_to_mobile_on_june_17": {
      "content_sha1": "7cd23f611cc43699e131ae3b01c25c7ad906b3fa",
      "data_file": "articles.jsonl",
      "fallback": "none",
      "fetch_status": "ok",
      "published_at": "2026-06-04T19:35:36",
      "saved_at": "2026-06-05T00:08:18+00:00",
      "source": "mobilegamer.biz",
      "source_key": "mobilegamer",
      "title": "Pokémon Champions is coming to mobile on June 17",
      "url": "https://mobilegamer.biz/pokemon-champions-is-coming-to-mobile-on-june-17/"
    },
    "subscribe_to_the_mobilegamer_biz_podcast_now": {
      "content_sha1": "0f0c083c063c4d0f941293b73ae7943497df133e",
      "data_file": "articles.jsonl",
      "fallback": "none",
      "fetch_status": "ok",
      "published_at": "2026-06-04T20:50:00",
      "saved_at": "2026-06-05T00:08:19+00:00",
      "source": "mobilegamer.biz",
      "source_key": "mobilegamer",
      "title": "On the podcast: Supercell, King and Sybo slam EU plan, Atari buys Hipster Whale, Zynga’s Mark Pincus on copycats, more",
      "url": "https://mobilegamer.biz/subscribe-to-the-mobilegamer-biz-podcast-now/"
    }
  }
}