{
  "items": {
    "215361": {
      "content_sha1": "5c68a4f726c30b0f8fc4cfdfbd5a4596662ee553",
      "data_file": "articles.jsonl",
      "fallback": "none",
      "fetch_status": "ok",
      "published_at": "2026-06-05T08:00:31",
      "saved_at": "2026-06-06T00:01:51+00:00",
      "source": "gcores.com",
      "source_key": "gcores",
      "title": "射击游戏《第三次世界大战》将于8月3日停服",
      "url": "https://www.gcores.com/articles/215361"
    },
    "215362": {
      "content_sha1": "8610f416bb63da255584a015efb5646d80148a3e",
      "data_file": "articles.jsonl",
      "fallback": "none",
      "fetch_status": "ok",
      "published_at": "2026-06-05T08:00:31",
      "saved_at": "2026-06-06T00:01:40+00:00",
      "source": "gcores.com",
      "source_key": "gcores",
      "title": "《行会 - 欧洲1410》Steam版将于7月16日发售",
      "url": "https://www.gcores.com/articles/215362"
    },
    "215363": {
      "content_sha1": "3696e9f869d4bc6b452e3afb627eacb2808c8eb3",
      "data_file": "articles.jsonl",
      "fallback": "none",
      "fetch_status": "ok",
      "published_at": "2026-06-05T08:00:31",
      "saved_at": "2026-06-06T00:01:45+00:00",
      "source": "gcores.com",
      "source_key": "gcores",
      "title": "化身特技车手：《特技演员：好莱坞》推出Steam商城页",
      "url": "https://www.gcores.com/articles/215363"
    },
    "215366": {
      "content_sha1": "ed208a7060c2d2da3a923deae4d95832f1e867f0",
      "data_file": "articles.jsonl",
      "fallback": "none",
      "fetch_status": "ok",
      "published_at": "2026-06-05T08:00:31",
      "saved_at": "2026-06-06T00:01:36+00:00",
      "source": "gcores.com",
      "source_key": "gcores",
      "title": "任天堂确认将推出可更换电池版本的Switch 2",
      "url": "https://www.gcores.com/articles/215366"
    },
    "215370": {
      "content_sha1": "29517f8aff9e213d7d6495f8fb37372b3eb5ea4c",
      "data_file": "articles.jsonl",
      "fallback": "none",
      "fetch_status": "ok",
      "published_at": "2026-06-05T08:00:31",
      "saved_at": "2026-06-06T00:01:31+00:00",
      "source": "gcores.com",
      "source_key": "gcores",
      "title": "《宝可梦 Champions》移动版宣布将于6月17日起陆续上线",
      "url": "https://www.gcores.com/articles/215370"
    },
    "215379": {
      "content_sha1": "a0927c8f1e3d3d5fcb13fb849669ef6c6f509eff",
      "data_file": "articles.jsonl",
      "fallback": "none",
      "fetch_status": "ok",
      "published_at": "2026-06-05T08:00:29",
      "saved_at": "2026-06-06T00:01:26+00:00",
      "source": "gcores.com",
      "source_key": "gcores",
      "title": "以《女神异闻录》“主角“猫猫化”为主题的周边商品将于6月4日起接受预订",
      "url": "https://www.gcores.com/articles/215379"
    },
    "215380": {
      "content_sha1": "99803eb03d37c0f60e37deca9589fd3cd604b205",
      "data_file": "articles.jsonl",
      "fallback": "none",
      "fetch_status": "ok",
      "published_at": "2026-06-05T08:00:29",
      "saved_at": "2026-06-06T00:01:21+00:00",
      "source": "gcores.com",
      "source_key": "gcores",
      "title": "国产多人动作肉鸽《失落城堡2》将于6月11日迎来1.0正式版",
      "url": "https://www.gcores.com/articles/215380"
    },
    "215381": {
      "content_sha1": "0f8b72190c1d802bcb1ceb232ad3acacfc19c1dc",
      "data_file": "articles.jsonl",
      "fallback": "none",
      "fetch_status": "ok",
      "published_at": "2026-06-05T08:00:29",
      "saved_at": "2026-06-06T00:01:16+00:00",
      "source": "gcores.com",
      "source_key": "gcores",
      "title": "Xbox公布六月初XGP游戏名单：包括《女神异闻录5：皇家版》等",
      "url": "https://www.gcores.com/articles/215381"
    },
    "215385": {
      "content_sha1": "0d309a75c8ade44a38b6158cc407b5e07a9aaa7a",
      "data_file": "articles.jsonl",
      "fallback": "none",
      "fetch_status": "ok",
      "published_at": "2026-06-05T08:00:29",
      "saved_at": "2026-06-06T00:01:08+00:00",
      "source": "gcores.com",
      "source_key": "gcores",
      "title": "专为游戏而生：英特尔锐炫G3系列分享会消息汇总",
      "url": "https://www.gcores.com/articles/215385"
    },
    "215391": {
      "content_sha1": "4488d835780cb3673e74b0e7b00b2b76d02dcc9b",
      "data_file": "articles.jsonl",
      "fallback": "none",
      "fetch_status": "ok",
      "published_at": "2026-06-05T08:00:29",
      "saved_at": "2026-06-06T00:01:00+00:00",
      "source": "gcores.com",
      "source_key": "gcores",
      "title": "《真・三国无双２ with 猛将传 Remastered》确定于2026年10月1日（四）发售",
      "url": "https://www.gcores.com/articles/215391"
    },
    "215393": {
      "content_sha1": "177bd9c539841c478eda29ecd2b0e3b53dbe1e1a",
      "data_file": "articles.jsonl",
      "fallback": "none",
      "fetch_status": "ok",
      "published_at": "2026-06-05T08:00:29",
      "saved_at": "2026-06-06T00:00:52+00:00",
      "source": "gcores.com",
      "source_key": "gcores",
      "title": "完全手绘：点击式冒险游戏《A Lost Man》将于6月26日发售",
      "url": "https://www.gcores.com/articles/215393"
    },
    "215397": {
      "content_sha1": "643227ff17c982839df30b1981d4d979cfeb51d2",
      "data_file": "articles.jsonl",
      "fallback": "none",
      "fetch_status": "ok",
      "published_at": "2026-06-05T08:00:29",
      "saved_at": "2026-06-06T00:00:43+00:00",
      "source": "gcores.com",
      "source_key": "gcores",
      "title": "《无限：六角穹顶战术》将于2026年秋季登陆Steam",
      "url": "https://www.gcores.com/articles/215397"
    },
    "215410": {
      "content_sha1": "8c2f687f15757338d0d120f862dd6b31dc51e2a8",
      "data_file": "articles.jsonl",
      "fallback": "none",
      "fetch_status": "ok",
      "published_at": "2026-06-05T08:00:29",
      "saved_at": "2026-06-06T00:00:37+00:00",
      "source": "gcores.com",
      "source_key": "gcores",
      "title": "《艾尔登法环 褪色者版》Switch 2版确认于2026年8月28日发售",
      "url": "https://www.gcores.com/articles/215410"
    },
    "215413": {
      "content_sha1": "288e1c8fb39a1b6fa4409e32642d8bdc114f76c0",
      "data_file": "articles.jsonl",
      "fallback": "none",
      "fetch_status": "ok",
      "published_at": "2026-06-05T10:00:29",
      "saved_at": "2026-06-06T00:02:06+00:00",
      "source": "gcores.com",
      "source_key": "gcores",
      "title": "V社宣布Steam Machine和Steam Frame将于夏季发售",
      "url": "https://www.gcores.com/articles/215413"
    },
    "215415": {
      "content_sha1": "a9e11faded87d6663bf69b77526dc468ff062d43",
      "data_file": "articles.jsonl",
      "fallback": "none",
      "fetch_status": "ok",
      "published_at": "2026-06-05T10:00:29",
      "saved_at": "2026-06-06T00:02:00+00:00",
      "source": "gcores.com",
      "source_key": "gcores",
      "title": "Epic喜加二：《征服之歌》及《恶棍水域》免费领",
      "url": "https://www.gcores.com/articles/215415"
    },
    "215416": {
      "content_sha1": "e01f13ae1e3a0b8e8aa3648eb5b89b73a52ded2b",
      "data_file": "articles.jsonl",
      "fallback": "none",
      "fetch_status": "ok",
      "published_at": "2026-06-05T10:00:29",
      "saved_at": "2026-06-06T00:01:55+00:00",
      "source": "gcores.com",
      "source_key": "gcores",
      "title": "《冰川时代6：熔岩危机》公布首个预告，将于2027年2月5日上映",
      "url": "https://www.gcores.com/articles/215416"
    },
    "215419": {
      "content_sha1": "6167cdaa7c3e0036583c5201c0bb344039c4f88b",
      "data_file": "articles.jsonl",
      "fallback": "none",
      "fetch_status": "ok",
      "published_at": "2026-06-05T11:00:29",
      "saved_at": "2026-06-06T00:02:17+00:00",
      "source": "gcores.com",
      "source_key": "gcores",
      "title": "未来007游戏或将由亚马逊游戏工作室打造",
      "url": "https://www.gcores.com/articles/215419"
    },
    "215420": {
      "content_sha1": "215c8272c3e0158549e372dbf147aa3820de6d32",
      "data_file": "articles.jsonl",
      "fallback": "none",
      "fetch_status": "ok",
      "published_at": "2026-06-05T11:00:29",
      "saved_at": "2026-06-06T00:02:12+00:00",
      "source": "gcores.com",
      "source_key": "gcores",
      "title": "可复用的方法论分享——创新游戏制作人专场议程公布！",
      "url": "https://www.gcores.com/articles/215420"
    },
    "215426": {
      "content_sha1": "96feda7197801e6f04b7cf7c466d1446e1cbc9e7",
      "data_file": "articles.jsonl",
      "fallback": "none",
      "fetch_status": "ok",
      "published_at": "2026-06-05T12:00:29",
      "saved_at": "2026-06-06T00:02:22+00:00",
      "source": "gcores.com",
      "source_key": "gcores",
      "title": "视觉小说新作《COCORO》公布OP动画，由人气声优羊宫妃那配音",
      "url": "https://www.gcores.com/articles/215426"
    },
    "215429": {
      "content_sha1": "53503faeaefc51013f2c73619b69e85a53b60456",
      "data_file": "articles.jsonl",
      "fallback": "none",
      "fetch_status": "ok",
      "published_at": "2026-06-05T13:00:29",
      "saved_at": "2026-06-06T00:02:39+00:00",
      "source": "gcores.com",
      "source_key": "gcores",
      "title": "Xbox首席执行官Asha Sharma表示：平台“必须拥有独占内容”",
      "url": "https://www.gcores.com/articles/215429"
    },
    "215430": {
      "content_sha1": "b81c864b3c4221efae6ebc5a457feb2896c74bb7",
      "data_file": "articles.jsonl",
      "fallback": "none",
      "fetch_status": "ok",
      "published_at": "2026-06-05T13:00:29",
      "saved_at": "2026-06-06T00:02:33+00:00",
      "source": "gcores.com",
      "source_key": "gcores",
      "title": "FIFA官方新作《FIFA World Cup 2026》6月11日登陆Netflix，订阅用户免费游玩",
      "url": "https://www.gcores.com/articles/215430"
    },
    "215431": {
      "content_sha1": "6b689c6d2d713e528542b6e0440435f716dd8b9f",
      "data_file": "articles.jsonl",
      "fallback": "none",
      "fetch_status": "ok",
      "published_at": "2026-06-05T13:00:29",
      "saved_at": "2026-06-06T00:02:27+00:00",
      "source": "gcores.com",
      "source_key": "gcores",
      "title": "知名爆料人billbil_kun称：《星球大战：零号连队》将于2026年8月27日发售",
      "url": "https://www.gcores.com/articles/215431"
    },
    "215432": {
      "content_sha1": "8a7aabf5c71040a7e20dfd7adf01ba8be0562ce2",
      "data_file": "articles.jsonl",
      "fallback": "none",
      "fetch_status": "ok",
      "published_at": "2026-06-05T14:00:21",
      "saved_at": "2026-06-06T00:02:54+00:00",
      "source": "gcores.com",
      "source_key": "gcores",
      "title": "《鬼泣》动画获 Netflix 续订第三季，确认将为最终季",
      "url": "https://www.gcores.com/articles/215432"
    },
    "215433": {
      "content_sha1": "8fcc5847d0e503403254361ad49bbb4a04e35b2e",
      "data_file": "articles.jsonl",
      "fallback": "none",
      "fetch_status": "ok",
      "published_at": "2026-06-05T14:00:21",
      "saved_at": "2026-06-06T00:02:49+00:00",
      "source": "gcores.com",
      "source_key": "gcores",
      "title": "《如龙》及《审判之眼》系列Steam促销：最高75%折扣，多款游戏平史低",
      "url": "https://www.gcores.com/articles/215433"
    },
    "215434": {
      "content_sha1": "d24285807eef3f3b53635efd52d4e2c45962135f",
      "data_file": "articles.jsonl",
      "fallback": "none",
      "fetch_status": "ok",
      "published_at": "2026-06-05T14:00:21",
      "saved_at": "2026-06-06T00:02:44+00:00",
      "source": "gcores.com",
      "source_key": "gcores",
      "title": "Take-Two CEO Strauss Zelnick现已加入《WWE 2K26》的可玩角色阵容",
      "url": "https://www.gcores.com/articles/215434"
    },
    "215435": {
      "content_sha1": "e2fd75be3014c5f4221d44dddfba4e81a88bfbd9",
      "data_file": "articles.jsonl",
      "fallback": "none",
      "fetch_status": "ok",
      "published_at": "2026-06-05T15:00:21",
      "saved_at": "2026-06-06T00:03:08+00:00",
      "source": "gcores.com",
      "source_key": "gcores",
      "title": "《城市：天际线 重制版 日本特别版》今秋登陆 PS5，收录三种日本主题 DLC",
      "url": "https://www.gcores.com/articles/215435"
    },
    "215439": {
      "content_sha1": "ddd6f4dbb9045ed02d5cbe89e51f0c09e6c7ced3",
      "data_file": "articles.jsonl",
      "fallback": "none",
      "fetch_status": "ok",
      "published_at": "2026-06-05T15:00:21",
      "saved_at": "2026-06-06T00:03:04+00:00",
      "source": "gcores.com",
      "source_key": "gcores",
      "title": "《2XKO》新英雄“锤石”6月10日参战，钩子与灯笼联动再现原作特色",
      "url": "https://www.gcores.com/articles/215439"
    },
    "215440": {
      "content_sha1": "97b42797757467bfa4b8b54ad855cdeb98b4ef06",
      "data_file": "articles.jsonl",
      "fallback": "none",
      "fetch_status": "ok",
      "published_at": "2026-06-05T15:00:21",
      "saved_at": "2026-06-06T00:02:59+00:00",
      "source": "gcores.com",
      "source_key": "gcores",
      "title": "《真理谭：黑暗城堡的女巫》试玩版正式上线Steam！也将参展6月份的Steam新品节",
      "url": "https://www.gcores.com/articles/215440"
    },
    "215442": {
      "content_sha1": "153d316ee40c5a9130b36c9d6e69fe908fdfff7c",
      "data_file": "articles.jsonl",
      "fallback": "none",
      "fetch_status": "ok",
      "published_at": "2026-06-05T16:00:21",
      "saved_at": "2026-06-06T00:03:23+00:00",
      "source": "gcores.com",
      "source_key": "gcores",
      "title": "互动影视作品《盛世天下》女帝篇定价公布，游戏将于6月9日发售",
      "url": "https://www.gcores.com/articles/215442"
    },
    "215443": {
      "content_sha1": "6be50039fcde7014f3f5aa6b4ccc867537003ce5",
      "data_file": "articles.jsonl",
      "fallback": "none",
      "fetch_status": "ok",
      "published_at": "2026-06-05T16:00:21",
      "saved_at": "2026-06-06T00:03:18+00:00",
      "source": "gcores.com",
      "source_key": "gcores",
      "title": "真人出演都市传说冒险游戏《AKIBA LOST (秋叶原迷踪) 》免费试玩版现已上线！",
      "url": "https://www.gcores.com/articles/215443"
    },
    "215445": {
      "content_sha1": "07dcb8fa68c8addf63c43c0bc16301ca9b839ae3",
      "data_file": "articles.jsonl",
      "fallback": "none",
      "fetch_status": "ok",
      "published_at": "2026-06-05T16:00:21",
      "saved_at": "2026-06-06T00:03:13+00:00",
      "source": "gcores.com",
      "source_key": "gcores",
      "title": "Atlus官方辟谣：《暗喻幻想 Retold》为冒充员工的账号发布的虚假信息",
      "url": "https://www.gcores.com/articles/215445"
    },
    "215458": {
      "content_sha1": "70447edea6c3d2eb7ed0cd7db140091242985f6f",
      "data_file": "articles.jsonl",
      "fallback": "none",
      "fetch_status": "ok",
      "published_at": "2026-06-05T19:00:21",
      "saved_at": "2026-06-06T00:03:39+00:00",
      "source": "gcores.com",
      "source_key": "gcores",
      "title": "《索尼克》35周年纪念音乐CD将于6月24日发售，收录22首歌曲",
      "url": "https://www.gcores.com/articles/215458"
    },
    "215459": {
      "content_sha1": "20dffb863d953bd13ec905ecc387224430d76427",
      "data_file": "articles.jsonl",
      "fallback": "none",
      "fetch_status": "ok",
      "published_at": "2026-06-05T19:00:21",
      "saved_at": "2026-06-06T00:03:34+00:00",
      "source": "gcores.com",
      "source_key": "gcores",
      "title": "首批搭载NVIDIA RTX Spark翻转本：Computex微星发布Prestige N16 Flip AI+",
      "url": "https://www.gcores.com/articles/215459"
    },
    "215460": {
      "content_sha1": "e46583273f29cfd4c91801ac70fe9d5bcbb2520e",
      "data_file": "articles.jsonl",
      "fallback": "none",
      "fetch_status": "ok",
      "published_at": "2026-06-05T19:00:21",
      "saved_at": "2026-06-06T00:03:28+00:00",
      "source": "gcores.com",
      "source_key": "gcores",
      "title": "Valve 发布 Steam 商店主页大型更新：界面翻新、新增个性化日历",
      "url": "https://www.gcores.com/articles/215460"
    }
  }
}